{
  "applications": "*",
  "changelogDate": "20230208061450",
  "dto": "mapstruct",
  "embedded": false,
  "entityTableName": "employee",
  "fields": [
    {
      "fieldName": "firstName",
      "fieldType": "String"
    },
    {
      "fieldName": "lastName",
      "fieldType": "String"
    },
    {
      "fieldName": "username",
      "fieldType": "String",
      "fieldValidateRules": ["required", "unique"]
    },
    {
      "fieldName": "password",
      "fieldType": "String",
      "fieldValidateRules": ["required"]
    },
    {
      "fieldName": "email",
      "fieldType": "String",
      "fieldValidateRules": ["unique"]
    },
    {
      "fieldName": "phone",
      "fieldType": "String"
    },
    {
      "fieldName": "mobile",
      "fieldType": "String"
    },
    {
      "fieldName": "department",
      "fieldType": "String"
    },
    {
      "fieldName": "designation",
      "fieldType": "String"
    },
    {
      "fieldName": "gender",
      "fieldType": "Gender",
      "fieldValues": "MALE (Male),FEMALE (Female),TRANSGENDER (Transgender)"
    },
    {
      "fieldName": "employeeId",
      "fieldType": "String",
      "fieldValidateRules": ["required"]
    },
    {
      "fieldName": "joindate",
      "fieldType": "Instant"
    },
    {
      "fieldName": "createdBy",
      "fieldType": "String"
    },
    {
      "fieldName": "createdOn",
      "fieldType": "Instant"
    },
    {
      "fieldName": "lastModified",
      "fieldType": "Instant"
    },
    {
      "fieldName": "lastModifiedBy",
      "fieldType": "String"
    },
    {
      "fieldName": "deleted",
      "fieldType": "Boolean"
    },
    {
      "fieldName": "reportedTo",
      "fieldType": "Long"
    },
    {
      "fieldName": "companyId",
      "fieldType": "Long"
    },
    {
      "fieldName": "branchId",
      "fieldType": "Long"
    },
    {
      "fieldName": "regionId",
      "fieldType": "Long"
    }
  ],
  "fluentMethods": true,
  "jpaMetamodelFiltering": true,
  "name": "Employee",
  "pagination": "pagination",
  "readOnly": false,
  "relationships": [],
  "service": "serviceClass"
}
